repox/__init__.py
repox/__version__.py
repox/repox.py
tests/__init__.py
tests/mocks.py
tests/tests.py
repox-0.0.3.dist-info/LICENSE
repox-0.0.3.dist-info/METADATA
repox-0.0.3.dist-info/WHEEL
repox-0.0.3.dist-info/top_level.txt
repox-0.0.3.dist-info/RECORD
