Metadata-Version: 2.1
Name: repox
Version: 0.0.3
Summary: a lightweight Repox client written in Python
Home-page: https://github.com/markpbaggett/pyrepox
Author: Mark Baggett
Author-email: mbagget1@utk.edu
Maintainer-email: mbagget1@utk.edu
License: UNKNOWN
Keywords: libraries,dpla,europeana,aggregators
Platform: UNKNOWN
Classifier: License :: OSI Approved :: GNU General Public License v3 (GPLv3)
Classifier: Programming Language :: Python :: 3.7
Classifier: Operating System :: OS Independent
Requires-Dist: requests (>=2.2.1)
Requires-Dist: xmltodict (>=0.11.0)
Requires-Dist: arrow (>=0.13.0)
Provides-Extra: docs
Requires-Dist: sphinx (>=1.4) ; extra == 'docs'
Requires-Dist: sphinxcontrib-napoleon (>=0.7) ; extra == 'docs'
Requires-Dist: recommonmark (>=0.4.0) ; extra == 'docs'
